foreman/__init__.py
foreman/foreman.py
sundarkid_foreman-0.1.2.dev0.dist-info/METADATA
sundarkid_foreman-0.1.2.dev0.dist-info/WHEEL
sundarkid_foreman-0.1.2.dev0.dist-info/top_level.txt
sundarkid_foreman-0.1.2.dev0.dist-info/RECORD
