Metadata-Version: 2.1
Name: sundarkid-foreman
Version: 0.1.2.dev0
Summary: UNKNOWN
Home-page: UNKNOWN
Author: sundarkid
Author-email: sundareswaran25@gmail.com
License: MIT
Platform: UNKNOWN
Requires-Dist: requests
